xchk_mysql_comparison_strategies/__init__.py
xchk_mysql_comparison_strategies/apps.py
xchk_mysql_comparison_strategies/solutions/other_simple_select.sql
xchk_mysql_comparison_strategies/solutions/simple_select.sql
xchk_mysql_comparison_strategies/strats.py
xchk_mysql_comparison_strategies/submitted_files/simple_select.sql
xchk_mysql_comparison_strategies/templates/xchk_mysql_comparison_strategies/xchk_mysql_comparison_strategies_json_1.json
xchk_mysql_comparison_strategies/templates/xchk_mysql_comparison_strategies/xchk_mysql_comparison_strategies_rendered_1.html
xchk_mysql_comparison_strategies/tests.py
xchk_mysql_comparison_strategies-0.0.2.dist-info/WHEEL
xchk_mysql_comparison_strategies-0.0.2.dist-info/METADATA
xchk_mysql_comparison_strategies-0.0.2.dist-info/RECORD
